typhoonw/__init__.py
typhoonw/auth.py
typhoonw/data.py
typhoonw/extensions.py
typhoonw/models.py
typhoonw/static/img1.jpg
typhoonw/static/logo.png
typhoonw/static/style.css
typhoonw/templates/base.html
typhoonw/templates/auth/login.html
typhoonw/templates/data/add_item.html
typhoonw/templates/data/index.html
typhoonw/templates/data/landing_intro.html
typhoonw/templates/data/parting_intro.html
typhoonw/templates/data/query.html
typhoonw-1.0.1.dist-info/METADATA
typhoonw-1.0.1.dist-info/WHEEL
typhoonw-1.0.1.dist-info/top_level.txt
typhoonw-1.0.1.dist-info/RECORD
