Metadata-Version: 2.1
Name: typhoonw
Version: 1.0.1
Summary: typhoon analysing website for yyp
Home-page: UNKNOWN
Author: dakele
Author-email: wmxy123@yeah.net
License: UNKNOWN
Platform: UNKNOWN
Classifier: Development Status :: 3 - Alpha
Classifier: Intended Audience :: Science/Research
Classifier: License :: OSI Approved :: MIT License
Requires-Python: >=2.7
Requires-Dist: Flask (==1.1.1)
Requires-Dist: Flask-SQLAlchemy (==2.4.1)
Requires-Dist: pytest (==4.6.8)
Requires-Dist: coverage (==5.0.1)
Requires-Dist: pymysql (==0.9.3)
Requires-Dist: cryptography (==2.8)
Requires-Dist: Flask-Excel (==0.0.7)
Requires-Dist: pyexcel-xlsx (==0.5.7)
Requires-Dist: pyexcel-xls (==0.5.8)
Requires-Dist: pyexcel-handsontable (==0.0.2)
Requires-Dist: flask-bootstrap (==3.3.7.1)
Requires-Dist: gunicorn (==19.10.0)
Requires-Dist: gevent (==1.4.0)
Requires-Dist: pip (==19.3.1)
Provides-Extra: dev
Requires-Dist: check-manifest ; extra == 'dev'
Provides-Extra: test
Requires-Dist: coverage (==5.0.1) ; extra == 'test'
